<?xml version="1.0" encoding="UTF-8" standalone="no"?>
<Dimap_Document>
  <Metadata_Identification>
    <METADATA_FORMAT version="2.0">DIMAP</METADATA_FORMAT>
    <METADATA_PROFILE>PHR_SENSOR</METADATA_PROFILE>
    <METADATA_SUBPROFILE>RPC</METADATA_SUBPROFILE>
    <METADATA_LANGUAGE>en</METADATA_LANGUAGE>
  </Metadata_Identification>
  <Rational_Function_Model>
    <Resource_Reference>
      <RESOURCE_TITLE version="2.1">NITF</RESOURCE_TITLE>
      <RESOURCE_ID>RPC00B</RESOURCE_ID>
    </Resource_Reference>
    <Global_RFM>
      <Direct_Model>
        <SAMP_NUM_COEFF_1>-0.001983743139624786</SAMP_NUM_COEFF_1>
        <SAMP_NUM_COEFF_2>0.9967049531717714</SAMP_NUM_COEFF_2>
        <SAMP_NUM_COEFF_3>-0.0004332554674778489</SAMP_NUM_COEFF_3>
        <SAMP_NUM_COEFF_4>-0.0008724860450893114</SAMP_NUM_COEFF_4>
        <SAMP_NUM_COEFF_5>0.001193642610011882</SAMP_NUM_COEFF_5>
        <SAMP_NUM_COEFF_6>-3.210473056760852e-05</SAMP_NUM_COEFF_6>
        <SAMP_NUM_COEFF_7>-1.172792214076809e-05</SAMP_NUM_COEFF_7>
        <SAMP_NUM_COEFF_8>0.002742708804100664</SAMP_NUM_COEFF_8>
        <SAMP_NUM_COEFF_9>-0.001400875127796085</SAMP_NUM_COEFF_9>
        <SAMP_NUM_COEFF_10>-2.548626815755099e-08</SAMP_NUM_COEFF_10>
        <SAMP_NUM_COEFF_11>-3.583884213035854e-08</SAMP_NUM_COEFF_11>
        <SAMP_NUM_COEFF_12>1.586430879356203e-05</SAMP_NUM_COEFF_12>
        <SAMP_NUM_COEFF_13>-1.266632446089129e-06</SAMP_NUM_COEFF_13>
        <SAMP_NUM_COEFF_14>1.87887512131266e-06</SAMP_NUM_COEFF_14>
        <SAMP_NUM_COEFF_15>4.424615912636356e-05</SAMP_NUM_COEFF_15>
        <SAMP_NUM_COEFF_16>0.0001962661272342434</SAMP_NUM_COEFF_16>
        <SAMP_NUM_COEFF_17>-8.121864489396553e-10</SAMP_NUM_COEFF_17>
        <SAMP_NUM_COEFF_18>-5.195370477991974e-08</SAMP_NUM_COEFF_18>
        <SAMP_NUM_COEFF_19>4.873099785891304e-08</SAMP_NUM_COEFF_19>
        <SAMP_NUM_COEFF_20>-1.669962983155902e-09</SAMP_NUM_COEFF_20>
        <SAMP_DEN_COEFF_1>1</SAMP_DEN_COEFF_1>
        <SAMP_DEN_COEFF_2>-0.0007562002423236437</SAMP_DEN_COEFF_2>
        <SAMP_DEN_COEFF_3>-0.001190977196003645</SAMP_DEN_COEFF_3>
        <SAMP_DEN_COEFF_4>3.027128342684178e-05</SAMP_DEN_COEFF_4>
        <SAMP_DEN_COEFF_5>-1.025648303439689e-05</SAMP_DEN_COEFF_5>
        <SAMP_DEN_COEFF_6>4.457267346860898e-08</SAMP_DEN_COEFF_6>
        <SAMP_DEN_COEFF_7>-3.456560863384679e-08</SAMP_DEN_COEFF_7>
        <SAMP_DEN_COEFF_8>-6.370757294418968e-06</SAMP_DEN_COEFF_8>
        <SAMP_DEN_COEFF_9>1.796295179475326e-06</SAMP_DEN_COEFF_9>
        <SAMP_DEN_COEFF_10>1.879015909521242e-06</SAMP_DEN_COEFF_10>
        <SAMP_DEN_COEFF_11>1.431695683881777e-09</SAMP_DEN_COEFF_11>
        <SAMP_DEN_COEFF_12>-1.385056791863796e-07</SAMP_DEN_COEFF_12>
        <SAMP_DEN_COEFF_13>2.643615984908325e-07</SAMP_DEN_COEFF_13>
        <SAMP_DEN_COEFF_14>-6.725049022222381e-09</SAMP_DEN_COEFF_14>
        <SAMP_DEN_COEFF_15>-3.332077792058572e-07</SAMP_DEN_COEFF_15>
        <SAMP_DEN_COEFF_16>-7.87619719858038e-07</SAMP_DEN_COEFF_16>
        <SAMP_DEN_COEFF_17>-4.471930978141676e-09</SAMP_DEN_COEFF_17>
        <SAMP_DEN_COEFF_18>9.956521157540678e-10</SAMP_DEN_COEFF_18>
        <SAMP_DEN_COEFF_19>3.156243142797665e-10</SAMP_DEN_COEFF_19>
        <SAMP_DEN_COEFF_20>1.16209812226248e-10</SAMP_DEN_COEFF_20>
        <LINE_NUM_COEFF_1>0.003264121093726507</LINE_NUM_COEFF_1>
        <LINE_NUM_COEFF_2>-0.005444143896317235</LINE_NUM_COEFF_2>
        <LINE_NUM_COEFF_3>-0.9946437809200458</LINE_NUM_COEFF_3>
        <LINE_NUM_COEFF_4>8.233239684889624e-05</LINE_NUM_COEFF_4>
        <LINE_NUM_COEFF_5>-0.001695756134303688</LINE_NUM_COEFF_5>
        <LINE_NUM_COEFF_6>-7.941464526621373e-07</LINE_NUM_COEFF_6>
        <LINE_NUM_COEFF_7>1.541846644082095e-06</LINE_NUM_COEFF_7>
        <LINE_NUM_COEFF_8>0.0005573025060646507</LINE_NUM_COEFF_8>
        <LINE_NUM_COEFF_9>-0.001852743154360669</LINE_NUM_COEFF_9>
        <LINE_NUM_COEFF_10>-1.299220706140567e-07</LINE_NUM_COEFF_10>
        <LINE_NUM_COEFF_11>1.079551752100942e-07</LINE_NUM_COEFF_11>
        <LINE_NUM_COEFF_12>3.076517922536298e-06</LINE_NUM_COEFF_12>
        <LINE_NUM_COEFF_13>-2.208592707545686e-05</LINE_NUM_COEFF_13>
        <LINE_NUM_COEFF_14>2.043429726223748e-07</LINE_NUM_COEFF_14>
        <LINE_NUM_COEFF_15>2.483393990146433e-05</LINE_NUM_COEFF_15>
        <LINE_NUM_COEFF_16>0.000127111946045009</LINE_NUM_COEFF_16>
        <LINE_NUM_COEFF_17>3.722721869776055e-05</LINE_NUM_COEFF_17>
        <LINE_NUM_COEFF_18>-7.457014107599165e-08</LINE_NUM_COEFF_18>
        <LINE_NUM_COEFF_19>2.122901274954192e-08</LINE_NUM_COEFF_19>
        <LINE_NUM_COEFF_20>-3.0791789219412e-09</LINE_NUM_COEFF_20>
        <LINE_DEN_COEFF_1>1</LINE_DEN_COEFF_1>
        <LINE_DEN_COEFF_2>-0.001665853775583783</LINE_DEN_COEFF_2>
        <LINE_DEN_COEFF_3>0.001394633365688969</LINE_DEN_COEFF_3>
        <LINE_DEN_COEFF_4>1.265420087406759e-06</LINE_DEN_COEFF_4>
        <LINE_DEN_COEFF_5>-1.032215598294982e-05</LINE_DEN_COEFF_5>
        <LINE_DEN_COEFF_6>7.453544425369515e-08</LINE_DEN_COEFF_6>
        <LINE_DEN_COEFF_7>1.838916165362883e-08</LINE_DEN_COEFF_7>
        <LINE_DEN_COEFF_8>-2.698049456694223e-05</LINE_DEN_COEFF_8>
        <LINE_DEN_COEFF_9>7.475895530988865e-05</LINE_DEN_COEFF_9>
        <LINE_DEN_COEFF_10>-3.744012761701478e-05</LINE_DEN_COEFF_10>
        <LINE_DEN_COEFF_11>1.934244693266725e-09</LINE_DEN_COEFF_11>
        <LINE_DEN_COEFF_12>1.02740534046702e-07</LINE_DEN_COEFF_12>
        <LINE_DEN_COEFF_13>2.23868169696962e-07</LINE_DEN_COEFF_13>
        <LINE_DEN_COEFF_14>1.257547928471298e-07</LINE_DEN_COEFF_14>
        <LINE_DEN_COEFF_15>-1.291685630457824e-07</LINE_DEN_COEFF_15>
        <LINE_DEN_COEFF_16>9.090576014435197e-08</LINE_DEN_COEFF_16>
        <LINE_DEN_COEFF_17>1.721321066142106e-08</LINE_DEN_COEFF_17>
        <LINE_DEN_COEFF_18>-4.74603513045823e-10</LINE_DEN_COEFF_18>
        <LINE_DEN_COEFF_19>-1.242923215843955e-08</LINE_DEN_COEFF_19>
        <LINE_DEN_COEFF_20>-9.898067823392657e-11</LINE_DEN_COEFF_20>
        <ERR_BIAS_X>0.0009134772478952632</ERR_BIAS_X>
        <ERR_BIAS_Y>0.0001826017396043292</ERR_BIAS_Y>
      </Direct_Model>
      <Inverse_Model>
        <SAMP_NUM_COEFF_1>0.001991633625548222</SAMP_NUM_COEFF_1>
        <SAMP_NUM_COEFF_2>1.003284624365643</SAMP_NUM_COEFF_2>
        <SAMP_NUM_COEFF_3>-0.0004463118257124248</SAMP_NUM_COEFF_3>
        <SAMP_NUM_COEFF_4>0.0008754353019442905</SAMP_NUM_COEFF_4>
        <SAMP_NUM_COEFF_5>0.001210929824171582</SAMP_NUM_COEFF_5>
        <SAMP_NUM_COEFF_6>2.784088311840359e-05</SAMP_NUM_COEFF_6>
        <SAMP_NUM_COEFF_7>-1.205786751569115e-05</SAMP_NUM_COEFF_7>
        <SAMP_NUM_COEFF_8>-0.002752001414153075</SAMP_NUM_COEFF_8>
        <SAMP_NUM_COEFF_9>0.001419254825838125</SAMP_NUM_COEFF_9>
        <SAMP_NUM_COEFF_10>1.438917149988221e-08</SAMP_NUM_COEFF_10>
        <SAMP_NUM_COEFF_11>1.327285271553086e-07</SAMP_NUM_COEFF_11>
        <SAMP_NUM_COEFF_12>-2.161813683333611e-06</SAMP_NUM_COEFF_12>
        <SAMP_NUM_COEFF_13>-9.224289382803695e-06</SAMP_NUM_COEFF_13>
        <SAMP_NUM_COEFF_14>-2.978093586142983e-06</SAMP_NUM_COEFF_14>
        <SAMP_NUM_COEFF_15>3.00538591638432e-05</SAMP_NUM_COEFF_15>
        <SAMP_NUM_COEFF_16>0.000201519483552592</SAMP_NUM_COEFF_16>
        <SAMP_NUM_COEFF_17>6.862235753204465e-10</SAMP_NUM_COEFF_17>
        <SAMP_NUM_COEFF_18>-1.583262475439875e-07</SAMP_NUM_COEFF_18>
        <SAMP_NUM_COEFF_19>-1.040070700238753e-07</SAMP_NUM_COEFF_19>
        <SAMP_NUM_COEFF_20>-2.54623355059553e-09</SAMP_NUM_COEFF_20>
        <SAMP_DEN_COEFF_1>1</SAMP_DEN_COEFF_1>
        <SAMP_DEN_COEFF_2>0.000763329069842148</SAMP_DEN_COEFF_2>
        <SAMP_DEN_COEFF_3>-0.001213974000556281</SAMP_DEN_COEFF_3>
        <SAMP_DEN_COEFF_4>-2.967162406379975e-05</SAMP_DEN_COEFF_4>
        <SAMP_DEN_COEFF_5>-2.14701848065549e-06</SAMP_DEN_COEFF_5>
        <SAMP_DEN_COEFF_6>9.752488766103202e-08</SAMP_DEN_COEFF_6>
        <SAMP_DEN_COEFF_7>-4.092533803659645e-08</SAMP_DEN_COEFF_7>
        <SAMP_DEN_COEFF_8>2.023524153464356e-06</SAMP_DEN_COEFF_8>
        <SAMP_DEN_COEFF_9>5.863547695198942e-07</SAMP_DEN_COEFF_9>
        <SAMP_DEN_COEFF_10>-2.977304907416412e-06</SAMP_DEN_COEFF_10>
        <SAMP_DEN_COEFF_11>-2.613657892209122e-09</SAMP_DEN_COEFF_11>
        <SAMP_DEN_COEFF_12>-1.517695219119706e-08</SAMP_DEN_COEFF_12>
        <SAMP_DEN_COEFF_13>-1.914274222920893e-07</SAMP_DEN_COEFF_13>
        <SAMP_DEN_COEFF_14>-1.018070414893509e-08</SAMP_DEN_COEFF_14>
        <SAMP_DEN_COEFF_15>3.798779974589225e-07</SAMP_DEN_COEFF_15>
        <SAMP_DEN_COEFF_16>1.683699560522801e-06</SAMP_DEN_COEFF_16>
        <SAMP_DEN_COEFF_17>7.278920975232651e-09</SAMP_DEN_COEFF_17>
        <SAMP_DEN_COEFF_18>-3.744325087067256e-11</SAMP_DEN_COEFF_18>
        <SAMP_DEN_COEFF_19>-2.803124508318453e-10</SAMP_DEN_COEFF_19>
        <SAMP_DEN_COEFF_20>1.691511973668657e-10</SAMP_DEN_COEFF_20>
        <LINE_NUM_COEFF_1>0.00327075992366219</LINE_NUM_COEFF_1>
        <LINE_NUM_COEFF_2>-0.005489159704651755</LINE_NUM_COEFF_2>
        <LINE_NUM_COEFF_3>-1.00536354914944</LINE_NUM_COEFF_3>
        <LINE_NUM_COEFF_4>7.798348372947222e-05</LINE_NUM_COEFF_4>
        <LINE_NUM_COEFF_5>0.001663402291212814</LINE_NUM_COEFF_5>
        <LINE_NUM_COEFF_6>-1.29004714582061e-07</LINE_NUM_COEFF_6>
        <LINE_NUM_COEFF_7>3.725823120489828e-07</LINE_NUM_COEFF_7>
        <LINE_NUM_COEFF_8>0.0005834813341945329</LINE_NUM_COEFF_8>
        <LINE_NUM_COEFF_9>-0.001887795206761557</LINE_NUM_COEFF_9>
        <LINE_NUM_COEFF_10>1.298054060951792e-07</LINE_NUM_COEFF_10>
        <LINE_NUM_COEFF_11>3.551377227354776e-08</LINE_NUM_COEFF_11>
        <LINE_NUM_COEFF_12>-1.110547379325431e-06</LINE_NUM_COEFF_12>
        <LINE_NUM_COEFF_13>-5.622518847615398e-06</LINE_NUM_COEFF_13>
        <LINE_NUM_COEFF_14>-2.058030865692245e-07</LINE_NUM_COEFF_14>
        <LINE_NUM_COEFF_15>-2.663377735369703e-05</LINE_NUM_COEFF_15>
        <LINE_NUM_COEFF_16>-0.0001329190744105895</LINE_NUM_COEFF_16>
        <LINE_NUM_COEFF_17>-3.767000422857088e-05</LINE_NUM_COEFF_17>
        <LINE_NUM_COEFF_18>2.228972579600419e-09</LINE_NUM_COEFF_18>
        <LINE_NUM_COEFF_19>-2.265223594173819e-10</LINE_NUM_COEFF_19>
        <LINE_NUM_COEFF_20>2.925099803925508e-09</LINE_NUM_COEFF_20>
        <LINE_DEN_COEFF_1>1</LINE_DEN_COEFF_1>
        <LINE_DEN_COEFF_2>0.001693252647445677</LINE_DEN_COEFF_2>
        <LINE_DEN_COEFF_3>0.001399376539570649</LINE_DEN_COEFF_3>
        <LINE_DEN_COEFF_4>1.145418688586073e-07</LINE_DEN_COEFF_4>
        <LINE_DEN_COEFF_5>-7.406085579569989e-06</LINE_DEN_COEFF_5>
        <LINE_DEN_COEFF_6>-3.491200443463045e-08</LINE_DEN_COEFF_6>
        <LINE_DEN_COEFF_7>1.277079697859484e-08</LINE_DEN_COEFF_7>
        <LINE_DEN_COEFF_8>2.116552877482329e-05</LINE_DEN_COEFF_8>
        <LINE_DEN_COEFF_9>-7.081790064846856e-05</LINE_DEN_COEFF_9>
        <LINE_DEN_COEFF_10>3.745606575610354e-05</LINE_DEN_COEFF_10>
        <LINE_DEN_COEFF_11>1.98485203977074e-10</LINE_DEN_COEFF_11>
        <LINE_DEN_COEFF_12>1.09563267654667e-07</LINE_DEN_COEFF_12>
        <LINE_DEN_COEFF_13>1.399700447838878e-06</LINE_DEN_COEFF_13>
        <LINE_DEN_COEFF_14>1.258429134880712e-07</LINE_DEN_COEFF_14>
        <LINE_DEN_COEFF_15>4.206726981300319e-07</LINE_DEN_COEFF_15>
        <LINE_DEN_COEFF_16>-2.471305937973469e-07</LINE_DEN_COEFF_16>
        <LINE_DEN_COEFF_17>-1.758501757918426e-08</LINE_DEN_COEFF_17>
        <LINE_DEN_COEFF_18>-1.10023332271477e-10</LINE_DEN_COEFF_18>
        <LINE_DEN_COEFF_19>1.248834974120937e-08</LINE_DEN_COEFF_19>
        <LINE_DEN_COEFF_20>1.260534762559114e-11</LINE_DEN_COEFF_20>
        <ERR_BIAS_ROW>0.000410537465912057</ERR_BIAS_ROW>
        <ERR_BIAS_COL>0.001533039459973221</ERR_BIAS_COL>
      </Inverse_Model>
      <RFM_Validity>
        <Direct_Model_Validity_Domain>
          <FIRST_ROW>1</FIRST_ROW>
          <FIRST_COL>1</FIRST_COL>
          <LAST_ROW>38380</LAST_ROW>
          <LAST_COL>40000</LAST_COL>
        </Direct_Model_Validity_Domain>
        <Inverse_Model_Validity_Domain>
          <FIRST_LON>-58.33666982585456</FIRST_LON>
          <FIRST_LAT>-33.25086813172416</FIRST_LAT>
          <LAST_LON>-58.1029882928706</LAST_LON>
          <LAST_LAT>-33.06895411040618</LAST_LAT>
        </Inverse_Model_Validity_Domain>
        <LONG_SCALE>0.1142967366403411</LONG_SCALE>
        <LONG_OFF>-58.22007888772087</LONG_OFF>
        <LAT_SCALE>0.08913664391583254</LAT_SCALE>
        <LAT_OFF>-33.1599480170111</LAT_OFF>
        <HEIGHT_SCALE>40</HEIGHT_SCALE>
        <HEIGHT_OFF>40</HEIGHT_OFF>
        <SAMP_SCALE>19999.5</SAMP_SCALE>
        <SAMP_OFF>20000.5</SAMP_OFF>
        <LINE_SCALE>19189.5</LINE_SCALE>
        <LINE_OFF>19190.5</LINE_OFF>
      </RFM_Validity>
    </Global_RFM>
  </Rational_Function_Model>
</Dimap_Document>